open_flash-1.0.23.dist-info/licenses/CITATION.cff
open_flash-1.0.23.dist-info/licenses/LICENSE
openflash/__init__.py
openflash/basic_region_geometry.py
openflash/body.py
openflash/domain.py
openflash/geometry.py
openflash/meem_engine.py
openflash/meem_problem.py
openflash/multi_constants.py
openflash/multi_equations.py
openflash/problem_cache.py
openflash/results.py
open_flash-1.0.23.dist-info/METADATA
open_flash-1.0.23.dist-info/WHEEL
open_flash-1.0.23.dist-info/top_level.txt
open_flash-1.0.23.dist-info/RECORD
