Metadata-Version: 2.4
Name: open-flash
Version: 1.0.23
Summary: A Python package for semi-analytical hydrodynamics modeling including matched eigenfunction expansion method
Author: SEA Lab
Project-URL: Homepage, https://github.com/symbiotic-engineering/semi-analytical-hydro.git
Keywords: matched eigenfunctions,hydrodynamics,semi-analytical
Classifier: Programming Language :: Python :: 3
Classifier: Programming Language :: Python :: 3.8
Classifier: Programming Language :: Python :: 3.9
Classifier: Programming Language :: Python :: 3.10
Classifier: Programming Language :: Python :: 3.11
Classifier: Programming Language :: Python :: 3.12
Classifier: Operating System :: OS Independent
Classifier: Intended Audience :: Science/Research
Classifier: Topic :: Scientific/Engineering :: Physics
Requires-Python: >=3.8
License-File: LICENSE
License-File: CITATION.cff
Requires-Dist: numpy>=1.21
Requires-Dist: scipy>=1.7
Requires-Dist: pandas>=1.5
Requires-Dist: matplotlib>=3.5
Requires-Dist: h5netcdf>=0.12
Requires-Dist: h5py>=3.0
Requires-Dist: xarray>=2023.0
Requires-Dist: streamlit>=1.0
Provides-Extra: dev
Requires-Dist: pytest>=7.0; extra == "dev"
Requires-Dist: pytest-cov; extra == "dev"
Requires-Dist: sphinx>=3.0; extra == "dev"
Requires-Dist: sphinx-rtd-theme>=0.5; extra == "dev"
Requires-Dist: sphinx-tabs>=1.0; extra == "dev"
Requires-Dist: sphinx_design>=0.0.8; extra == "dev"
Requires-Dist: sphinx-copybutton; extra == "dev"
Requires-Dist: sphinx-last-updated-by-git; extra == "dev"
Requires-Dist: nbsphinx>=0.8; extra == "dev"
Requires-Dist: jupyter>=1.0.0; extra == "dev"
Requires-Dist: ipykernel; extra == "dev"
Requires-Dist: twine>=4.0; extra == "dev"
Requires-Dist: build>=0.8; extra == "dev"
Requires-Dist: readme_renderer>=30.0; extra == "dev"
Requires-Dist: watchdog>=3.0; extra == "dev"
Requires-Dist: black>=23.0; extra == "dev"
Requires-Dist: ruff>=0.0.280; extra == "dev"
Provides-Extra: hydro
Requires-Dist: capytaine>=2.2; extra == "hydro"
Dynamic: license-file
